flex_algo/__init__.py
flex_algo/array_utils.py
flex_algo/doubly_linked_list.py
flex_algo/linked_list.py
flex_algo/priority_queue.py
flex_algo/search.py
flex_algo/sort.py
flex_algo/stack.py
flex_algo/stacks_queue.py
flex_algo/str_utils.py
flex_algo-0.0.6.dist-info/METADATA
flex_algo-0.0.6.dist-info/WHEEL
flex_algo-0.0.6.dist-info/licenses/LICENCE
flex_algo-0.0.6.dist-info/RECORD
